dnszonetest/__init__.py
dnszonetest/cli.py
dnszonetest/exceptions.py
dnszonetest/main.py
dnszonetest-1.1.1.dist-info/DESCRIPTION.rst
dnszonetest-1.1.1.dist-info/METADATA
dnszonetest-1.1.1.dist-info/RECORD
dnszonetest-1.1.1.dist-info/WHEEL
dnszonetest-1.1.1.dist-info/entry_points.txt
dnszonetest-1.1.1.dist-info/metadata.json
dnszonetest-1.1.1.dist-info/top_level.txt
