Metadata-Version: 2.0
Name: dnszonetest
Version: 1.1.1
Summary: DNS Zone Test tests a DNS zone file agaist a given name server.
Home-page: https://github.com/maartenq/dnszonetest
Author: Maarten Diemel
Author-email: maarten@maartendiemel.nl
License: ISC license
Keywords: dnszonetest
Platform: UNKNOWN
Classifier: Development Status :: 5 - Production/Stable
Classifier: Environment :: Console
Classifier: Intended Audience :: System Administrators
Classifier: License :: OSI Approved :: ISC License (ISCL)
Classifier: Natural Language :: English
Classifier: Programming Language :: Python :: 2
Classifier: Programming Language :: Python :: 2.6
Classifier: Programming Language :: Python :: 2.7
Classifier: Programming Language :: Python :: 3
Classifier: Programming Language :: Python :: 3.3
Classifier: Programming Language :: Python :: 3.4
Classifier: Programming Language :: Python :: 3.5
Classifier: Topic :: Documentation :: Sphinx
Classifier: Topic :: Utilities
Requires-Dist: dnspython
